{"360\u56e2\u8d2d":{"\u978d\u5c71":"an_shan","\u5b89\u9633":"an_yang","\u5b89\u5e86":"an_qing","\u6fb3\u95e8":"ao_men","\u5b89\u5eb7":"an_kang","\u963f\u514b\u82cf":"a_ke_su","\u5317\u4eac":"bei_jing","\u4fdd\u5b9a":"bao_ding","\u5305\u5934":"bao_tou","\u868c\u57e0":"beng_bu","\u5b9d\u9e21":"bao_ji","\u5317\u6d77":"bei_hai","\u6ee8\u5dde":"bin_zhou","\u672c\u6eaa":"ben_xi","\u5df4\u97f3\u90ed\u695e":"ba_yin_guo_le","\u4fdd\u5c71":"bao_shan","\u4eb3\u5dde":"bo_zhou","\u767d\u5c71":"bai_shan","\u767e\u8272":"bai_se","\u767d\u57ce":"bai_cheng","\u6210\u90fd":"cheng_du","\u91cd\u5e86":"chong_qing","\u957f\u6c99":"chang_sha","\u957f\u6625":"chang_chun","\u5e38\u5dde":"chang_zhou","\u6ca7\u5dde":"cang_zhou","\u5e38\u5fb7":"chang_de","\u5e38\u719f":"chang_shu","\u6f6e\u5dde":"chao_zhou","\u5de2\u6e56":"chao_hu","\u90f4\u5dde":"chen_zhou","\u6ec1\u5dde":"chu_zhou","\u627f\u5fb7":"cheng_de","\u8d64\u5cf0":"chi_feng","\u957f\u6cbb":"chang_zhi","\u6c60\u5dde":"chi_zhou","\u695a\u96c4":"chu_xiong","\u660c\u5409":"chang_ji","\u4ece\u5316":"cong_hua","\u5927\u8fde":"da_lian","\u4e1c\u839e":"dong_guan","\u4e1c\u8425":"dong_ying","\u5fb7\u5dde":"de_zhou","\u5927\u5e86":"da_qing","\u5fb7\u9633":"de_yang","\u5927\u540c":"da_tong","\u4e39\u4e1c":"dan_dong","\u4e39\u9633":"dan_yang","\u5927\u7406":"da_li","\u8fbe\u5dde":"da_zhou","\u4e1c\u9633":"dong_yang","\u9102\u5dde":"e_zhou","\u9102\u5c14\u591a\u65af":"e_er_duo_si","\u5ce8\u7709\u5c71":"e_mei_shan","\u798f\u5dde":"fu_zhou","\u4f5b\u5c71":"fo_shan","\u629a\u987a":"fu_shun","\u961c\u9633":"fu_yang","\u961c\u65b0":"fu_xin","\u629a\u5dde":"fu_zhou_","\u51e4\u51f0":"feng_huang","\u5bcc\u9633":"fu_yang_1","\u5e7f\u5dde":"guang_zhou","\u8d35\u9633":"gui_yang","\u6842\u6797":"gui_lin","\u8d63\u5dde":"gan_zhou","\u8d35\u6e2f":"gui_gang","\u5e7f\u5143":"guang_yuan","\u5e7f\u5b89":"guang_an","\u676d\u5dde":"hang_zhou","\u5408\u80a5":"he_fei","\u54c8\u5c14\u6ee8":"ha_er_bin","\u6d77\u53e3":"hai_kou","\u90af\u90f8":"han_dan","\u60e0\u5dde":"hui_zhou","\u547c\u548c\u6d69\u7279":"hu_he_hao_te","\u6e56\u5dde":"hu_zhou","\u6dee\u5b89":"huai_an","\u8861\u9633":"heng_yang","\u6dee\u5357":"huai_nan","\u8861\u6c34":"heng_shui","\u6dee\u5317":"huai_bei","\u83cf\u6cfd":"he_ze","\u9ec4\u77f3":"huang_shi","\u6cb3\u6e90":"he_yuan","\u846b\u82a6\u5c9b":"hu_lu_dao","\u9ec4\u5c71":"huang_shan","\u9ec4\u5188":"huang_guang","\u6000\u5316":"huai_hua","\u6c49\u4e2d":"han_zhong","\u9e64\u58c1":"he_bi","\u7ea2\u6cb3":"hong_he","\u6cb3\u6c60":"he_chi","\u547c\u4f26\u8d1d\u5c14":"hu_lun_bei_er","\u9ed1\u6cb3":"hei_he","\u9e64\u5c97":"he_gang","\u82b1\u90fd":"hua_du","\u6d77\u5b81":"hai_ning","\u6d4e\u5357":"ji_nan","\u6d4e\u5b81":"ji_ning","\u5609\u5174":"jia_xing","\u6c5f\u95e8":"jiang_men","\u91d1\u534e":"jin_hua","\u5409\u6797":"ji_lin","\u9526\u5dde":"jin_zhou","\u7126\u4f5c":"jiao_zuo","\u6c5f\u9634":"jiang_yin","\u4e5d\u6c5f":"jiu_jiang","\u8346\u5dde":"jing_zhou","\u664b\u4e2d":"jin_zhong","\u664b\u57ce":"jin_cheng","\u664b\u6c5f":"jin_jiang","\u63ed\u9633":"jie_yang","\u666f\u5fb7\u9547":"jing_de_zhen","\u5409\u5b89":"ji__an","\u4f73\u6728\u65af":"jia_mu_si","\u8346\u95e8":"jing_men","\u9e21\u897f":"ji_xi","\u9152\u6cc9":"jiu_quan","\u4e5d\u5be8\u6c9f":"jiu_zhai_gou","\u6606\u660e":"kun_ming","\u6606\u5c71":"kun_shan","\u5f00\u5c01":"kai_feng","\u514b\u62c9\u739b\u4f9d":"ke_la_ma_yi","\u6d1b\u9633":"luo_yang","\u5170\u5dde":"lan_zhou","\u4e34\u6c82":"lin_yi","\u5eca\u574a":"lang_fang","\u67f3\u5dde":"liu_zhou","\u8fde\u4e91\u6e2f":"lian_yun_gang","\u4e34\u6c7e":"lin_fen","\u804a\u57ce":"liao_cheng","\u4e3d\u6c34":"li_shui","\u9f99\u5ca9":"long_yan","\u4e50\u5c71":"le_shan","\u83b1\u829c":"lai_wu","\u4e34\u5b89":"lin_an","\u4e3d\u6c5f":"li_jiang","\u6f2f\u6cb3":"luo_he","\u6cf8\u5dde":"lu_zhou","\u5415\u6881":"lv_liang","\u8fbd\u9633":"liao_yang","\u5a04\u5e95":"lou_di","\u62c9\u8428":"la_sa","\u51c9\u5c71":"liang_shan","\u8fbd\u6e90":"liao_yuan","\u516d\u5b89":"liu_an","\u7ef5\u9633":"mian_yang","\u7261\u4e39\u6c5f":"mu_dan_jiang","\u9a6c\u978d\u5c71":"ma_an_shan","\u8302\u540d":"mao_ming","\u6885\u5dde":"mei_zhou","\u7709\u5c71":"mei_shan","\u5357\u4eac":"nan_jing","\u5b81\u6ce2":"ning_bo","\u5357\u660c":"nan_chang","\u5357\u5b81":"nan_ning","\u5357\u901a":"nan_tong","\u5357\u9633":"nan_yang","\u5b81\u5fb7":"ning_de","\u5357\u5145":"nan_chong","\u5357\u5e73":"nan_ping","\u5185\u6c5f":"nei_jiang","\u8386\u7530":"pu_tian","\u840d\u4e61":"ping_xiang","\u5e73\u9876\u5c71":"ping_ding_shan","\u76d8\u9526":"pan_jin","\u6fee\u9633":"pu_yang","\u6500\u679d\u82b1":"pan_zhi_hua","\u5e73\u51c9":"ping_liang","\u5e73\u9065":"ping_yao","\u9752\u5c9b":"qing_dao","\u6cc9\u5dde":"quan_zhou","\u79e6\u7687\u5c9b":"qin_huang_dao","\u9f50\u9f50\u54c8\u5c14":"qi_qi_haer","\u6e05\u8fdc":"qing_yuan","\u8862\u5dde":"qu_zhou","\u66f2\u9756":"qu_jing","\u94a6\u5dde":"qin_zhou","\u5168\u56fd":"quan_guo","\u65e5\u7167":"ri_zhao","\u4e0a\u6d77":"shang_hai","\u6df1\u5733":"shen_zhen","\u6c88\u9633":"shen_yang","\u82cf\u5dde":"su_zhou","\u77f3\u5bb6\u5e84":"shi_jia_zhuang","\u7ecd\u5174":"shao_xing","\u6c55\u5934":"shan_tou","\u4e09\u4e9a":"san_ya","\u97f6\u5173":"shao_guan","\u5341\u5830":"shi_yan","\u5bbf\u8fc1":"su_qian","\u987a\u5fb7":"shun_de","\u4e0a\u9976":"shang_rao","\u4e09\u660e":"san_ming","\u4e09\u95e8\u5ce1":"san_men_xia","\u5546\u4e18":"shang_qiu","\u6c55\u5c3e":"shan_wei","\u56db\u5e73":"si_ping","\u6714\u5dde":"shuo_zhou","\u5bbf\u5dde":"su_zhou_","\u90b5\u9633":"shao_yang","\u9042\u5b81":"sui_ning","\u53cc\u9e2d\u5c71":"shuang_ya_shan","\u968f\u5dde":"sui_zhou","\u677e\u539f":"song_yuan","\u77f3\u72ee":"shi_shi","\u7ee5\u5316":"sui_hua","\u5546\u6d1b":"shang_luo","\u5929\u6d25":"tian_jin","\u592a\u539f":"tai_yuan","\u5510\u5c71":"tang_shan","\u6cf0\u5b89":"tai_an","\u6cf0\u5dde":"tai_zhou_2","\u53f0\u5dde":"tai_zhou_1","\u94dc\u9675":"tong_ling","\u94c1\u5cad":"tie_ling","\u5858\u6cbd":"tang_gu","\u901a\u5316":"tong_hua","\u901a\u8fbd":"tong_liao","\u5929\u6c34":"tian_shui","\u6b66\u6c49":"wu_han","\u65e0\u9521":"wu_xi","\u6f4d\u574a":"wei_fang","\u6e29\u5dde":"wen_zhou","\u5a01\u6d77":"wei_hai","\u829c\u6e56":"wu_hu","\u4e4c\u9c81\u6728\u9f50":"wu_lu_mu_qi","\u5434\u6c5f":"wu_jiang","\u6e2d\u5357":"wei_nan","\u6b66\u5937\u5c71":"wu_yi_shan","\u4e07\u5dde":"wan_zhou","\u68a7\u5dde":"wu_zhou","\u897f\u5b89":"xi_an","\u53a6\u95e8":"xia_men","\u5f90\u5dde":"xu_zhou","\u8944\u9633":"xiang_yang","\u65b0\u4e61":"xin_xiang","\u54b8\u9633":"xian_yang","\u6e58\u6f6d":"xiang_tan","\u897f\u5b81":"xi_ning","\u90a2\u53f0":"xing_tai","\u9999\u6e2f":"xiang_gang","\u4fe1\u9633":"xin_yang","\u8bb8\u660c":"xu_chang","\u5b5d\u611f":"xiao_gan","\u65b0\u4f59":"xin_yu","\u5ffb\u5dde":"xin_zhou","\u5ba3\u57ce":"xuan_cheng","\u54b8\u5b81":"xian_ning","\u6e58\u897f":"xiang_xi","\u626c\u5dde":"yang_zhou","\u70df\u53f0":"yan_tai","\u76d0\u57ce":"yan_cheng","\u8fd0\u57ce":"yun_cheng","\u94f6\u5ddd":"yin_chuan","\u5b9c\u660c":"yi_chang","\u5cb3\u9633":"yue_yang","\u4e49\u4e4c":"yi_wu","\u8425\u53e3":"ying_kou","\u9633\u6c5f":"yang_jiang","\u4e91\u6d6e":"yun_fu","\u5ef6\u5409":"yan_ji","\u5b9c\u6625":"yi_chun_shi","\u7389\u6eaa":"yu_xi","\u7389\u6797":"yu_lin","\u5b9c\u5bbe":"yi_bin","\u76ca\u9633":"yi_yang","\u9633\u6cc9":"yang_quan","\u4f0a\u6625":"yi_chun","\u6986\u6797":"yu_lin_1","\u6c38\u5dde":"yong_zhou","\u4f0a\u7281":"yi_li","\u5ef6\u5b89":"yan_an","\u96c5\u5b89":"ya_an","\u9633\u6714":"yang_shuo","\u90d1\u5dde":"zheng_zhou","\u6dc4\u535a":"zi_bo","\u4e2d\u5c71":"zhong_shan","\u73e0\u6d77":"zhu_hai","\u9547\u6c5f":"zhen_jiang","\u682a\u6d32":"zhu_zhou","\u6f33\u5dde":"zhang_zhou","\u8087\u5e86":"zhao_qing","\u6e5b\u6c5f":"zhan_jiang","\u5f20\u5bb6\u6e2f":"zhang_jia_gang","\u5f20\u5bb6\u53e3":"zhang_jia_kou","\u821f\u5c71":"zhou_shan","\u67a3\u5e84":"zao_zhuang","\u9075\u4e49":"zun_yi","\u9a7b\u9a6c\u5e97":"zhu_ma_dian","\u5468\u53e3":"zhou_kou","\u81ea\u8d21":"zi_gong","\u671d\u9633":"zhao_yang","\u8d44\u9633":"zi_yang","\u5f20\u5bb6\u754c":"zhang_jia_jie"}}